cxn/__about__.py
cxn/__init__.py
cxn/cli.py
cxn/providers.py
cxn-0.0.5.dist-info/METADATA
cxn-0.0.5.dist-info/WHEEL
cxn-0.0.5.dist-info/entry_points.txt
cxn-0.0.5.dist-info/licenses/LICENSE.txt
cxn-0.0.5.dist-info/RECORD
