Metadata-Version: 2.3
Name: cxn
Version: 0.0.5
Summary: CXN (short for Connection) is a lightweight command-line tool to verify connectivity between services
Project-URL: Documentation, https://github.com/lykhvar/cxn#readme
Project-URL: Issues, https://github.com/lykhvar/cxn/issues
Project-URL: Source, https://github.com/lykhvar/cxn
Author-email: Artem Lykhvar <me@a10r.com>
License-Expression: MIT
License-File: LICENSE.txt
Keywords: automation,cli,command-line,tooling,utility
Classifier: Development Status :: 4 - Beta
Classifier: Programming Language :: Python
Classifier: Programming Language :: Python :: 3.8
Classifier: Programming Language :: Python :: 3.9
Classifier: Programming Language :: Python :: 3.10
Classifier: Programming Language :: Python :: 3.11
Classifier: Programming Language :: Python :: 3.12
Classifier: Programming Language :: Python :: Implementation :: CPython
Classifier: Programming Language :: Python :: Implementation :: PyPy
Requires-Python: >=3.8
